{
  "id": "ca194117-e7d5-4836-a96d-dd1beecd9832",
  "prevId": "00000000-0000-0000-0000-000000000000",
  "version": "7",
  "dialect": "postgresql",
  "tables": {
    "public.seats": {
      "name": "seats",
      "schema": "",
      "columns": {
        "id": {
          "name": "id",
          "type": "varchar",
          "primaryKey": true,
          "notNull": true
        },
        "group_number": {
          "name": "group_number",
          "type": "integer",
          "primaryKey": false,
          "notNull": true
        },
        "table_number": {
          "name": "table_number",
          "type": "integer",
          "primaryKey": false,
          "notNull": true
        },
        "seat_number": {
          "name": "seat_number",
          "type": "integer",
          "primaryKey": false,
          "notNull": true
        },
        "student_name": {
          "name": "student_name",
          "type": "text",
          "primaryKey": false,
          "notNull": false
        }
      },
      "indexes": {},
      "foreignKeys": {},
      "compositePrimaryKeys": {},
      "uniqueConstraints": {},
      "policies": {},
      "checkConstraints": {},
      "isRLSEnabled": false
    }
  },
  "enums": {},
  "schemas": {},
  "sequences": {},
  "roles": {},
  "policies": {},
  "views": {},
  "_meta": {
    "columns": {},
    "schemas": {},
    "tables": {}
  }
}